skywalking/__init__.py
skywalking/config.py
skywalking/decorators.py
skywalking/loggings.py
skywalking/agent/__init__.py
skywalking/agent/protocol/__init__.py
skywalking/agent/protocol/grpc.py
skywalking/agent/protocol/http.py
skywalking/agent/protocol/interceptors.py
skywalking/agent/protocol/kafka.py
skywalking/bootstrap/__init__.py
skywalking/bootstrap/cli/__init__.py
skywalking/bootstrap/cli/sw_python.py
skywalking/bootstrap/cli/utility/__init__.py
skywalking/bootstrap/cli/utility/runner.py
skywalking/bootstrap/loader/__init__.py
skywalking/bootstrap/loader/sitecustomize.py
skywalking/client/__init__.py
skywalking/client/grpc.py
skywalking/client/http.py
skywalking/client/kafka.py
skywalking/command/__init__.py
skywalking/command/base_command.py
skywalking/command/command_service.py
skywalking/command/profile_task_command.py
skywalking/command/executors/__init__.py
skywalking/command/executors/command_executor.py
skywalking/command/executors/noop_command_executor.py
skywalking/command/executors/profile_task_command_executor.py
skywalking/log/__init__.py
skywalking/log/formatter.py
skywalking/log/sw_logging.py
skywalking/plugins/__init__.py
skywalking/plugins/sw_aiohttp.py
skywalking/plugins/sw_celery.py
skywalking/plugins/sw_django.py
skywalking/plugins/sw_elasticsearch.py
skywalking/plugins/sw_falcon.py
skywalking/plugins/sw_fastapi.py
skywalking/plugins/sw_flask.py
skywalking/plugins/sw_http_server.py
skywalking/plugins/sw_kafka.py
skywalking/plugins/sw_mysqlclient.py
skywalking/plugins/sw_psycopg.py
skywalking/plugins/sw_psycopg2.py
skywalking/plugins/sw_pymongo.py
skywalking/plugins/sw_pymysql.py
skywalking/plugins/sw_pyramid.py
skywalking/plugins/sw_rabbitmq.py
skywalking/plugins/sw_redis.py
skywalking/plugins/sw_requests.py
skywalking/plugins/sw_sanic.py
skywalking/plugins/sw_tornado.py
skywalking/plugins/sw_urllib3.py
skywalking/plugins/sw_urllib_request.py
skywalking/profile/__init__.py
skywalking/profile/profile_constants.py
fast_skywalking-1.6.2.dist-info/LICENSE
fast_skywalking-1.6.2.dist-info/METADATA
fast_skywalking-1.6.2.dist-info/NOTICE
fast_skywalking-1.6.2.dist-info/WHEEL
fast_skywalking-1.6.2.dist-info/entry_points.txt
fast_skywalking-1.6.2.dist-info/top_level.txt
fast_skywalking-1.6.2.dist-info/RECORD
